<?xml version="1.0" encoding="utf-8" ?>
<LevelData>

  <!-- Information to draw the interior, walkable area of the room -->
  <!-- The boolean UseExterior allows the game to load in the regular exterior for all rooms except Room14 -->

  -<Interior>
    <UseExterior>True</UseExterior>
    <Rectangle>547,198,192,112</Rectangle>
  </Interior>

  <!--Monsters-->
  -<Monster Name="Keese" Spawn="52 144"/>
  -<Monster Name="Keese" Spawn="164 144"/>
  -<Monster Name="Keese" Spawn="176 104"/>
  -<Monster Name="Keese" Spawn="108 104"/>
  -<Monster Name="Keese" Spawn="128 144"/>


  <!-- Items -->
  <!--Blocks -->
  -<Block Name="Block" Spawn="112 128" Size="32 48" />
  <!-- Doors -->
  -<Door LeadsTo="Room0" Name="Wall" Side="Left" Destroyable="false"/>
  -<Door LeadsTo="Room6" Name="OpenDoor" Side="Right" Destroyable="false"/>
  -<Door LeadsTo="Room9" Name="OpenDoor" Side="Up" Destroyable="false"/>
  -<Door LeadsTo="Room0" Name="Wall" Side="Down" Destroyable="false"/>


</LevelData>